{
  "recentFiles": [
    {
      "basename": "docusaurus使用",
      "path": "docs/开发/博客搭建/docusaurus使用.md"
    },
    {
      "basename": "面向对象",
      "path": "docs/开发/后端/Go/面向对象.md"
    },
    {
      "basename": "Hertz",
      "path": "docs/开发/后端/Go/框架学习/Hertz.md"
    },
    {
      "basename": "Git学习",
      "path": "docs/开发/其他杂项/Git学习.md"
    },
    {
      "basename": "GORM框架学习",
      "path": "docs/开发/后端/Go/框架学习/GORM框架学习.md"
    },
    {
      "basename": "gin框架路由学习",
      "path": "docs/开发/后端/Go/框架学习/gin框架路由学习.md"
    },
    {
      "basename": "环境配置",
      "path": "docs/开发/后端/Go/环境配置.md"
    },
    {
      "basename": "堆",
      "path": "docs/开发/ACM/堆.md"
    },
    {
      "basename": "BM1 反转链表",
      "path": "docs/开发/ACM/牛客面试Top100/链表/BM1 反转链表.md"
    },
    {
      "basename": "BM2 链表内指定区间反转",
      "path": "docs/开发/ACM/牛客面试Top100/链表/BM2 链表内指定区间反转.md"
    },
    {
      "basename": "BM16 删除有序链表中重复的元素-II",
      "path": "docs/开发/ACM/牛客面试Top100/链表/BM16 删除有序链表中重复的元素-II.md"
    },
    {
      "basename": "BM4 合并两个排序的链表",
      "path": "docs/开发/ACM/牛客面试Top100/链表/BM4 合并两个排序的链表.md"
    },
    {
      "basename": "BM6 判断链表中是否有环",
      "path": "docs/开发/ACM/牛客面试Top100/链表/BM6 判断链表中是否有环.md"
    },
    {
      "basename": "BM8 链表中倒数最后k个结点",
      "path": "docs/开发/ACM/牛客面试Top100/链表/BM8 链表中倒数最后k个结点.md"
    },
    {
      "basename": "BM10 两个链表的第一个公共结点",
      "path": "docs/开发/ACM/牛客面试Top100/链表/BM10 两个链表的第一个公共结点.md"
    },
    {
      "basename": "BM12 单链表的排序",
      "path": "docs/开发/ACM/牛客面试Top100/链表/BM12 单链表的排序.md"
    },
    {
      "basename": "BM13 判断一个链表是否为回文结构",
      "path": "docs/开发/ACM/牛客面试Top100/链表/BM13 判断一个链表是否为回文结构.md"
    },
    {
      "basename": "BM14 链表的奇偶重排",
      "path": "docs/开发/ACM/牛客面试Top100/链表/BM14 链表的奇偶重排.md"
    },
    {
      "basename": "BM15 删除有序链表中重复的元素-I",
      "path": "docs/开发/ACM/牛客面试Top100/链表/BM15 删除有序链表中重复的元素-I.md"
    },
    {
      "basename": "aboutMe",
      "path": "src/aboutMe.md"
    },
    {
      "basename": "博客优化改造",
      "path": "src/docs/开发/博客搭建/博客优化改造.md"
    },
    {
      "basename": "docusaurus使用",
      "path": "src/docs/开发/博客搭建/docusaurus使用.md"
    },
    {
      "basename": "一分钱不花,炫酷博客带回家",
      "path": "src/docs/开发/博客搭建/一分钱不花,炫酷博客带回家.md"
    },
    {
      "basename": "README",
      "path": "src/docs/README.md"
    },
    {
      "basename": "React组件",
      "path": "src/docs/开发/前端/react/React组件.md"
    },
    {
      "basename": "React交互",
      "path": "src/docs/开发/前端/react/React交互.md"
    },
    {
      "basename": "README",
      "path": "src/README.md"
    },
    {
      "basename": "论文",
      "path": "src/论文.md"
    },
    {
      "basename": "论文3",
      "path": "src/论文3.md"
    },
    {
      "basename": "论文架构",
      "path": "src/论文架构.md"
    },
    {
      "basename": "GORM框架学习",
      "path": "src/docs/开发/后端/Go/框架学习/GORM框架学习.md"
    },
    {
      "basename": "面向对象",
      "path": "src/docs/开发/后端/Go/面向对象.md"
    },
    {
      "basename": "gin框架路由学习",
      "path": "src/docs/开发/后端/Go/框架学习/gin框架路由学习.md"
    },
    {
      "basename": "常用函数",
      "path": "src/docs/开发/ACM/常用函数.md"
    },
    {
      "basename": "BM16 删除有序链表中重复的元素-II",
      "path": "src/docs/开发/ACM/牛客面试Top100/链表/BM16 删除有序链表中重复的元素-II.md"
    },
    {
      "basename": "BM15 删除有序链表中重复的元素-I",
      "path": "src/docs/开发/ACM/牛客面试Top100/链表/BM15 删除有序链表中重复的元素-I.md"
    },
    {
      "basename": "堆",
      "path": "src/docs/开发/ACM/堆.md"
    },
    {
      "basename": "README",
      "path": "node_modules/sitemap/README.md"
    },
    {
      "basename": "2025-04-06",
      "path": "book/计划/2025-04-06.md"
    },
    {
      "basename": "2025-04-03",
      "path": "book/计划/2025-04-03.md"
    },
    {
      "basename": "2025-04-02",
      "path": "book/计划/2025-04-02.md"
    },
    {
      "basename": "2025-04-01",
      "path": "book/计划/2025-04-01.md"
    },
    {
      "basename": "2025-03-31",
      "path": "book/计划/2025/3月/2025-03-31.md"
    },
    {
      "basename": "Day_template",
      "path": "book/模板/Day_template.md"
    },
    {
      "basename": "重点目标",
      "path": "book/知识笔记/渗透/SRC挖掘/萤石安全/重点目标.md"
    },
    {
      "basename": "工具",
      "path": "book/知识笔记/渗透/工具/工具.md"
    },
    {
      "basename": "ysoserial使用",
      "path": "book/知识笔记/渗透/工具/ysoserial使用.md"
    },
    {
      "basename": "外网打点工具概览",
      "path": "book/知识笔记/渗透/工具/外网打点工具概览.md"
    },
    {
      "basename": "内网",
      "path": "book/知识笔记/渗透/内网/内网.md"
    }
  ],
  "omittedPaths": [],
  "omittedTags": [],
  "updateOn": "file-open",
  "omitBookmarks": false
}